app/__init__.py
app/__main__.py
app/main.py
app/server.py
orange_typecast_api_mcp_server-0.1.0.dist-info/METADATA
orange_typecast_api_mcp_server-0.1.0.dist-info/WHEEL
orange_typecast_api_mcp_server-0.1.0.dist-info/entry_points.txt
orange_typecast_api_mcp_server-0.1.0.dist-info/RECORD
