Metadata-Version: 2.4
Name: orange-typecast-api-mcp-server
Version: 0.1.0
Summary: MCP Server for typecast-api
Author-email: Hyunseung Lee <hyunseung@neosapience.com>
Requires-Python: >=3.12
Requires-Dist: click
Requires-Dist: httpx
Requires-Dist: mcp
Requires-Dist: sounddevice
Requires-Dist: soundfile
